flavor/__init__.py
flavor/__main__.py
flavor/_version.py
flavor/cache.py
flavor/cli.py
flavor/console.py
flavor/exceptions.py
flavor/locking.py
flavor/output.py
flavor/package.py
flavor/verification.py
flavor/commands/__init__.py
flavor/commands/extract.py
flavor/commands/ingredients.py
flavor/commands/inspect.py
flavor/commands/keygen.py
flavor/commands/package.py
flavor/commands/utils.py
flavor/commands/verify.py
flavor/commands/workenv.py
flavor/config/__init__.py
flavor/config/config.py
flavor/config/defaults.py
flavor/config/manager.py
flavor/ingredients/__init__.py
flavor/ingredients/binary_loader.py
flavor/ingredients/manager.py
flavor/ingredients/bin/flavor-go-builder-0.0.1000-2-darwin_amd64
flavor/ingredients/bin/flavor-go-launcher-0.0.1000-2-darwin_amd64
flavor/ingredients/bin/flavor-rs-builder-0.0.1000-2-darwin_amd64
flavor/ingredients/bin/flavor-rs-launcher-0.0.1000-2-darwin_amd64
flavor/packaging/__init__.py
flavor/packaging/keys.py
flavor/packaging/orchestrator.py
flavor/packaging/orchestrator_ingredients.py
flavor/packaging/python/__init__.py
flavor/packaging/python/dependency_resolver.py
flavor/packaging/python/dist_manager.py
flavor/packaging/python/environment_builder.py
flavor/packaging/python/packager.py
flavor/packaging/python/pypapip_manager.py
flavor/packaging/python/slot_builder.py
flavor/packaging/python/uv_manager.py
flavor/packaging/python/wheel_builder.py
flavor/psp/__init__.py
flavor/psp/protocols.py
flavor/psp/security.py
flavor/psp/format_2025/__init__.py
flavor/psp/format_2025/backends.py
flavor/psp/format_2025/builder.py
flavor/psp/format_2025/constants.py
flavor/psp/format_2025/environment.py
flavor/psp/format_2025/executor.py
flavor/psp/format_2025/extraction.py
flavor/psp/format_2025/handlers.py
flavor/psp/format_2025/index.py
flavor/psp/format_2025/keys.py
flavor/psp/format_2025/launcher.py
flavor/psp/format_2025/operations.py
flavor/psp/format_2025/pspf_builder.py
flavor/psp/format_2025/reader.py
flavor/psp/format_2025/slots.py
flavorpack-0.0.1000.post2.dist-info/licenses/LICENSE
flavorpack-0.0.1000.post2.dist-info/METADATA
flavorpack-0.0.1000.post2.dist-info/WHEEL
flavorpack-0.0.1000.post2.dist-info/entry_points.txt
flavorpack-0.0.1000.post2.dist-info/top_level.txt
flavorpack-0.0.1000.post2.dist-info/RECORD
