Metadata-Version: 2.4
Name: flavorpack
Version: 0.0.1000.post2
Summary: Flavor Pack packaging system implementing Progressive Secure Package Format (PSPF/2025)
Author-email: Tim Perkins <code@tim.life>
Maintainer-email: "provide.io" <code@provide.io>
License-Expression: Apache-2.0
Project-URL: Homepage, https://github.com/provide-io/flavor
Keywords: packaging,pspf,flavor,executable,bundle
Classifier: Development Status :: 3 - Alpha
Classifier: Intended Audience :: Developers
Classifier: Programming Language :: Python :: 3
Classifier: Programming Language :: Python :: 3.11
Classifier: Programming Language :: Python :: 3.12
Classifier: Programming Language :: Python :: 3.13
Classifier: Programming Language :: Python :: 3.14
Classifier: Topic :: Software Development :: Build Tools
Classifier: Topic :: Security :: Cryptography
Classifier: Topic :: System :: Archiving :: Packaging
Requires-Python: >=3.11
License-File: LICENSE
Requires-Dist: provide-foundation[all]>=0.0.0.dev0
Requires-Dist: pip>=25.2
Requires-Dist: uv>=0.8.13
Dynamic: license-file
